{"intents": [
    {"tag": "saludo",
     "patterns": ["Hola", "Buenas", "Que tal", "Hey", "Buenos dias"],
     "responses": ["Hola"]
    },
    {"tag": "despedida",
     "patterns": ["Adiós", "Hasta luego", "Hasta otra", "Adios"],
     "responses": ["Adiós!"]
    },
    {"tag": "gracias",
     "patterns": ["Gracias", "Muchas gracias", "Gracias por la ayuda", "Gracias, solucionado"],
     "responses": ["Encantado de ayudar!"]
    },
    {"tag": "crearcuenta",
    "patterns": ["cómo puedo crear una cuenta?", "quisiera crear una cuenta", "puedes crearme una cuenta?", "me indicas cómo crear una cuenta?", "dónde puedo crear una cuenta?"],
    "responses": ["Puedes crear una cuenta haciendo click en el botón de arriba a la derecha"]
    },
    {"tag": "desactivarcuenta",
    "patterns": ["puedo desactivar mi cuenta?", "me gustaría descativar mi cuenta", "quiero borrar mi cuenta"],
    "responses": ["En tu perfil puedes encontrar la opción de eliminar cuenta"]
    }
]
}